README.md
setup.py
castomui/__init__.py
castomui/inputkb.py
castomui.egg-info/PKG-INFO
castomui.egg-info/SOURCES.txt
castomui.egg-info/dependency_links.txt
castomui.egg-info/top_level.txt