Metadata-Version: 2.1
Name: castomui
Version: 1.0
Summary: a python package for TUI 
Author: HSS2011
Author-email: hackersam2011@qq.com
Keywords: python,TUI,terminal,ui,windows,mac,linux
Classifier: Development Status :: 1 - Planning
Classifier: Intended Audience :: Developers
Classifier: Programming Language :: Python :: 3
Classifier: Operating System :: Unix
Classifier: Operating System :: MacOS :: MacOS X
Classifier: Operating System :: Microsoft :: Windows
